pretty_j1939/__init__.py
pretty_j1939/parse.py
pretty_j1939-0.0.1.data/scripts/create_j1939db-json.py
pretty_j1939-0.0.1.data/scripts/pretty_j1939.py
pretty_j1939-0.0.1.dist-info/LICENSE
pretty_j1939-0.0.1.dist-info/METADATA
pretty_j1939-0.0.1.dist-info/WHEEL
pretty_j1939-0.0.1.dist-info/top_level.txt
pretty_j1939-0.0.1.dist-info/RECORD
