Metadata-Version: 2.1
Name: pretty-j1939
Version: 0.0.1
Summary: python libs and scripts for pretty-printing J1939 logs
Home-page: https://github.com/nmfta-repo/pretty_j1939
Author: "Ben Gardiner <ben.gardiner@nmfta.org>", "Jeremy Daily <jeremy.daily@colostate.edu>"
Author-email: ben.gardiner@nmfta.org
License: UNKNOWN
Platform: UNKNOWN
Classifier: Programming Language :: Python :: 3
Classifier: Operating System :: OS Independent
Requires-Dist: asteval
Requires-Dist: defusedxml
Requires-Dist: unidecode
Requires-Dist: xlrd
Requires-Dist: bitstring
